sioDict/__init__.py
sioDict/base.py
sioDict/etc.py
sioDict/simple.py
sioDict/wrapper.py
sioDict/variants/toml.py
sioDict-0.4.1.dist-info/LICENSE
sioDict-0.4.1.dist-info/METADATA
sioDict-0.4.1.dist-info/WHEEL
sioDict-0.4.1.dist-info/top_level.txt
sioDict-0.4.1.dist-info/RECORD
