Metadata-Version: 2.1
Name: sioDict
Version: 0.4.1
Summary: Super Charged Io Dicts
Author: ZackaryW
License: MIT
Requires-Python: >=3.6
License-File: LICENSE
Requires-Dist: orjson
Requires-Dist: toml
